[
  {
    "clicks": 0,
    "color": "DarkRed"
  },
  {
    "clicks": 0,
    "color": "SeaShell"
  },
  {
    "clicks": 0,
    "color": "MenuHighlight"
  },
  {
    "clicks": 0,
    "color": "OliveDrab"
  },
  {
    "clicks": 0,
    "color": "ControlLight"
  },
  {
    "clicks": 0,
    "color": "Yellow"
  },
  {
    "clicks": 0,
    "color": "LightGoldenrodYellow"
  },
  {
    "clicks": 0,
    "color": "ControlDarkDark"
  },
  {
    "clicks": 0,
    "color": "Highlight"
  },
  {
    "clicks": 0,
    "color": "SteelBlue"
  }
]